cloudsec/__init__.py
cloudsec/backends/__init__.py
cloudsec/backends/cvc5sec.py
cloudsec/backends/z3sec.py
cloudsec/cloud.py
cloudsec/core.py
cloudsecpy-0.1.1.dist-info/LICENSE
cloudsecpy-0.1.1.dist-info/METADATA
cloudsecpy-0.1.1.dist-info/WHEEL
cloudsecpy-0.1.1.dist-info/RECORD
