Metadata-Version: 2.1
Name: cloudsecpy
Version: 0.1.1
Summary: Library and toolkit for formally analyzing security policies in cloud systems using Python.
Author: Joe Stubbs
Author-email: jstubbs@tacc.utexas.edu
Requires-Python: >=3.8,<4.0
Classifier: Programming Language :: Python :: 3
Classifier: Programming Language :: Python :: 3.8
Classifier: Programming Language :: Python :: 3.9
Classifier: Programming Language :: Python :: 3.10
Classifier: Programming Language :: Python :: 3.11
Requires-Dist: backcall (==0.2.0)
Requires-Dist: boto (==2.49.0)
Requires-Dist: cvc5 (==1.0.1)
Requires-Dist: decorator (==5.0.9)
Requires-Dist: ipython (==7.16.1)
Requires-Dist: ipython-genutils (==0.2.0)
Requires-Dist: jedi (==0.17.2)
Requires-Dist: parso (==0.7.1)
Requires-Dist: pexpect (==4.8.0)
Requires-Dist: pickleshare (==0.7.5)
Requires-Dist: prompt-toolkit (==3.0.20)
Requires-Dist: ptyprocess (==0.7.0)
Requires-Dist: pygments (==2.10.0)
Requires-Dist: six (==1.16.0)
Requires-Dist: traitlets (==4.3.3)
Requires-Dist: wcwidth (==0.2.5)
Requires-Dist: z3-solver (==4.8.12.0)
